leximetry/__init__.py
leximetry/__main__.py
leximetry/py.typed
leximetry/cli/__init__.py
leximetry/cli/cli_main.py
leximetry/cli/rich_styles.py
leximetry/docs/leximetry.md
leximetry/docs/regen_rubric.py
leximetry/docs/scoring_rubric.json
leximetry/docs/update_readme.py
leximetry/eval/evaluate_text.py
leximetry/eval/metrics_model.py
leximetry/eval/report_output.py
leximetry/eval/size_stats.py
leximetry-0.0.1.dist-info/METADATA
leximetry-0.0.1.dist-info/WHEEL
leximetry-0.0.1.dist-info/entry_points.txt
leximetry-0.0.1.dist-info/licenses/LICENSE
leximetry-0.0.1.dist-info/RECORD
